django_taggit_forms-0.1.1.dist-info/DESCRIPTION.rst
django_taggit_forms-0.1.1.dist-info/METADATA
django_taggit_forms-0.1.1.dist-info/metadata.json
django_taggit_forms-0.1.1.dist-info/RECORD
django_taggit_forms-0.1.1.dist-info/top_level.txt
django_taggit_forms-0.1.1.dist-info/WHEEL
taggit_forms/__init__.py
taggit_forms/admin.py
taggit_forms/conf.py
taggit_forms/forms.py
taggit_forms/models.py
taggit_forms/urls.py
taggit_forms/utils.py
taggit_forms/views.py
taggit_forms/migrations/__init__.py
taggit_forms/templates/taggit_forms/form.html
taggit_forms/templatetags/__init__.py
taggit_forms/templatetags/taggitforms.py
